ezurl/__init__.py
ezurl/ezurllib.py
ezurl-0.1.3.25.dist-info/DESCRIPTION.rst
ezurl-0.1.3.25.dist-info/METADATA
ezurl-0.1.3.25.dist-info/RECORD
ezurl-0.1.3.25.dist-info/WHEEL
ezurl-0.1.3.25.dist-info/metadata.json
ezurl-0.1.3.25.dist-info/top_level.txt
