Metadata-Version: 1.1
Name: ezurl
Version: 0.1.3.25
Summary: URL Generation for Python
Home-page: https://github.com/Dolphman/ezurl
Author: Joshua Walters
Author-email: therealdolphman@gmail.com
License: MIT
Keywords: URL Generation,Python URL generation,Python URL
Platform: UNKNOWN
Classifier: License :: OSI Approved :: MIT License
Classifier: Operating System :: OS Independent
Classifier: Topic :: Utilities
Classifier: Programming Language :: Python :: 2.7
Classifier: Programming Language :: Python :: 3
Classifier: Programming Language :: Python :: 3.0
Classifier: Programming Language :: Python :: 3.1
Classifier: Programming Language :: Python :: 3.2
Classifier: Programming Language :: Python :: 3.3
Classifier: Programming Language :: Python :: 3.4
Classifier: Programming Language :: Python :: 3.5
